pipen_poplog.py
pipen_poplog-1.1.4.dist-info/METADATA
pipen_poplog-1.1.4.dist-info/WHEEL
pipen_poplog-1.1.4.dist-info/entry_points.txt
pipen_poplog-1.1.4.dist-info/licenses/LICENSE
pipen_poplog-1.1.4.dist-info/RECORD
